emailr/__init__.py
emailr/client.py
emailr/errors.py
emailr/http.py
emailr/py.typed
emailr/types.py
emailr/resources/__init__.py
emailr/resources/api_keys.py
emailr/resources/broadcasts.py
emailr/resources/contacts.py
emailr/resources/domains.py
emailr/resources/emails.py
emailr/resources/forwarding_rules.py
emailr/resources/metrics.py
emailr/resources/segments.py
emailr/resources/settings.py
emailr/resources/smtp.py
emailr/resources/templates.py
emailr/resources/webhooks.py
emailr-1.1.0.dist-info/METADATA
emailr-1.1.0.dist-info/WHEEL
emailr-1.1.0.dist-info/top_level.txt
emailr-1.1.0.dist-info/RECORD
