Metadata-Version: 2.4
Name: emailr
Version: 1.1.0
Summary: Official Emailr API SDK for Python
Author-email: Emailr <support@emailr.dev>
License: MIT
Project-URL: Homepage, https://emailr.dev
Project-URL: Documentation, https://docs.emailr.dev
Project-URL: Repository, https://github.com/emailr-dev/emailr
Project-URL: Changelog, https://github.com/emailr-dev/emailr/blob/main/CHANGELOG.md
Keywords: email,api,sdk,emailr,transactional-email
Classifier: Development Status :: 4 - Beta
Classifier: Intended Audience :: Developers
Classifier: License :: OSI Approved :: MIT License
Classifier: Operating System :: OS Independent
Classifier: Programming Language :: Python :: 3
Classifier: Programming Language :: Python :: 3.8
Classifier: Programming Language :: Python :: 3.9
Classifier: Programming Language :: Python :: 3.10
Classifier: Programming Language :: Python :: 3.11
Classifier: Programming Language :: Python :: 3.12
Classifier: Topic :: Communications :: Email
Classifier: Topic :: Software Development :: Libraries :: Python Modules
Classifier: Typing :: Typed
Requires-Python: >=3.8
Requires-Dist: httpx>=0.24.0
Provides-Extra: dev
Requires-Dist: pytest>=7.0; extra == "dev"
Requires-Dist: pytest-asyncio>=0.21; extra == "dev"
Requires-Dist: pytest-httpx>=0.21; extra == "dev"
Requires-Dist: mypy>=1.0; extra == "dev"
Requires-Dist: ruff>=0.1.0; extra == "dev"
